llm_steer.py
llm_steer-2.0.1.dist-info/LICENSE
llm_steer-2.0.1.dist-info/METADATA
llm_steer-2.0.1.dist-info/WHEEL
llm_steer-2.0.1.dist-info/top_level.txt
llm_steer-2.0.1.dist-info/RECORD
