Metadata-Version: 2.1
Name: llm-steer
Version: 2.0.1
Summary: Steer LLM outputs towards a certain topic/subject and enhance response capabilities using activation engineering by adding steer vectors
Home-page: https://github.com/Mihaiii/llm_steer
Author: Mihai Chirculescu
Author-email: apropodemine@gmail.com
License: UNKNOWN
Platform: UNKNOWN
License-File: LICENSE
Requires-Dist: transformers
